plone.app.transmogrifier-3.0.1-py3.11-nspkg.pth
plone/app/transmogrifier/.htpasswd-users
plone/app/transmogrifier/__init__.py
plone/app/transmogrifier/browserdefault.py
plone/app/transmogrifier/browserdefault.rst
plone/app/transmogrifier/configure.zcml
plone/app/transmogrifier/datesupdater.py
plone/app/transmogrifier/datesupdater.rst
plone/app/transmogrifier/default-content.csv
plone/app/transmogrifier/mimeencapsulator.py
plone/app/transmogrifier/mimeencapsulator.rst
plone/app/transmogrifier/pathfixer.py
plone/app/transmogrifier/pathfixer.rst
plone/app/transmogrifier/portaltransforms.py
plone/app/transmogrifier/portaltransforms.rst
plone/app/transmogrifier/redirector.csv
plone/app/transmogrifier/redirector.py
plone/app/transmogrifier/redirector.rst
plone/app/transmogrifier/reindexobject.py
plone/app/transmogrifier/reindexobject.rst
plone/app/transmogrifier/tests.py
plone/app/transmogrifier/uidupdater.py
plone/app/transmogrifier/uidupdater.rst
plone/app/transmogrifier/urlnormalizer.py
plone/app/transmogrifier/urlnormalizer.rst
plone/app/transmogrifier/utils.py
plone/app/transmogrifier/versioning.py
plone/app/transmogrifier/versioning.rst
plone/app/transmogrifier/workflowupdater.py
plone/app/transmogrifier/workflowupdater.rst
plone/app/transmogrifier/xmlwalker.cfg
plone/app/transmogrifier/empty-site/.gitignore
plone.app.transmogrifier-3.0.1.dist-info/METADATA
plone.app.transmogrifier-3.0.1.dist-info/WHEEL
plone.app.transmogrifier-3.0.1.dist-info/namespace_packages.txt
plone.app.transmogrifier-3.0.1.dist-info/top_level.txt
plone.app.transmogrifier-3.0.1.dist-info/RECORD
