Metadata-Version: 2.1
Name: plone.app.transmogrifier
Version: 3.0.1
Summary: Plone blueprints for collective.transmogrifier pipelines
Home-page: https://github.com/collective/plone.app.transmogrifier
Author: Jarn
Author-email: info@jarn.com
License: GPL
Project-URL: PyPI, https://pypi.python.org/pypi/plone.app.transmogrifier
Project-URL: Source, https://github.com/collective/plone.app.transmogrifier
Project-URL: Tracker, https://github.com/collective/plone.app.transmogrifier/issues
Keywords: content import filtering plone
Classifier: Development Status :: 6 - Mature
Classifier: Environment :: Web Environment
Classifier: Framework :: Plone :: 5.2
Classifier: Framework :: Plone :: 6.0
Classifier: Framework :: Plone :: Addon
Classifier: Framework :: Plone
Classifier: Framework :: Zope2
Classifier: Framework :: Zope3
Classifier: License :: OSI Approved :: GNU General Public License (GPL)
Classifier: License :: OSI Approved :: GNU General Public License v2 (GPLv2)
Classifier: Programming Language :: Python :: 3.7
Classifier: Programming Language :: Python :: 3.8
Classifier: Programming Language :: Python :: 3.9
Classifier: Programming Language :: Python :: 3.10
Classifier: Programming Language :: Python :: 3.11
Classifier: Programming Language :: Python
Classifier: Topic :: Software Development :: Libraries :: Application Frameworks
Classifier: Topic :: Software Development :: Libraries :: Python Modules
Requires-Python: >=3.7
Requires-Dist: Plone
Requires-Dist: collective.transmogrifier (>=3.0.0)
Requires-Dist: plone.uuid
Requires-Dist: setuptools
Requires-Dist: zope.component
Provides-Extra: test
Requires-Dist: zope.testrunner ; extra == 'test'
